mosaik_components/pv/__init__.py
mosaik_components/pv/common.py
mosaik_components/pv/configurations.py
mosaik_components/pv/photovoltaic.py
mosaik_components/pv/photovoltaic_simulator.py
mosaik_pvlib-1.0.dist-info/LICENSE
mosaik_pvlib-1.0.dist-info/METADATA
mosaik_pvlib-1.0.dist-info/WHEEL
mosaik_pvlib-1.0.dist-info/RECORD
